__init__.py
ddadevops/LICENSE
ddadevops/__init__.py
ddadevops/aws_mfa_mixin.py
ddadevops/c4k_build.py
ddadevops/credential.py
ddadevops/devops_build.py
ddadevops/devops_image_build.py
ddadevops/devops_terraform_build.py
ddadevops/provs_k3s_build.py
ddadevops/release_mixin.py
ddadevops/application/__init__.py
ddadevops/application/image_build_service.py
ddadevops/application/release_mixin_services.py
ddadevops/application/terraform_service.py
ddadevops/domain/__init__.py
ddadevops/domain/artifact.py
ddadevops/domain/build_file.py
ddadevops/domain/c4k.py
ddadevops/domain/common.py
ddadevops/domain/credentials.py
ddadevops/domain/devops_factory.py
ddadevops/domain/image.py
ddadevops/domain/init_service.py
ddadevops/domain/provider_aws.py
ddadevops/domain/provider_digitalocean.py
ddadevops/domain/provider_hetzner.py
ddadevops/domain/provs_k3s.py
ddadevops/domain/release.py
ddadevops/domain/terraform.py
ddadevops/domain/version.py
ddadevops/infrastructure/__init__.py
ddadevops/infrastructure/infrastructure.py
ddadevops/infrastructure/repository.py
ddadevops/src/main/resources/docker/image/resources/install_functions.sh
ddadevops/src/main/resources/docker/image/resources/install_functions_alpine.sh
ddadevops/src/main/resources/docker/image/resources/install_functions_debian.sh
ddadevops/src/main/resources/terraform/aws_backend.tf
ddadevops/src/main/resources/terraform/aws_backend_wkms_vars.tf
ddadevops/src/main/resources/terraform/aws_backend_wokms_vars.tf
ddadevops/src/main/resources/terraform/aws_provider.tf
ddadevops/src/main/resources/terraform/aws_provider_vars.tf
ddadevops/src/main/resources/terraform/do_backend.tf
ddadevops/src/main/resources/terraform/do_backend_vars.tf
ddadevops/src/main/resources/terraform/do_provider.tf
ddadevops/src/main/resources/terraform/do_provider_vars.tf
ddadevops/src/main/resources/terraform/hetzner_provider.tf
ddadevops/src/main/resources/terraform/hetzner_provider_vars.tf
ddadevops/src/main/resources/terraform/provider_registry.tf
ddadevops-4.15.0.dist-info/METADATA
ddadevops-4.15.0.dist-info/WHEEL
ddadevops-4.15.0.dist-info/namespace_packages.txt
ddadevops-4.15.0.dist-info/top_level.txt
ddadevops-4.15.0.dist-info/zip-safe
ddadevops-4.15.0.dist-info/RECORD
