Metadata-Version: 2.1
Name: ddadevops
Version: 4.15.0
Summary: tools to support builds combining gopass, terraform, dda-pallet, aws & hetzner-cloud
Home-page: https://repo.prod.meissa.de/meissa/dda-devops-build
Author: meissa GmbH
Author-email: buero@meissa-gmbh.de
Maintainer: 
Maintainer-email: 
License: Apache Software License
Classifier: License :: OSI Approved :: Apache Software License
Classifier: Programming Language :: Python
Classifier: Programming Language :: Python :: 3
Classifier: Programming Language :: Python :: 3.8
Classifier: Programming Language :: Python :: 3.10
Classifier: Operating System :: POSIX :: Linux
Classifier: Operating System :: OS Independent
Classifier: Development Status :: 5 - Production/Stable
Classifier: Environment :: Console
Classifier: Intended Audience :: Developers
Classifier: License :: OSI Approved :: Apache Software License
Classifier: Topic :: Software Development :: Build Tools
Classifier: Topic :: Software Development :: Quality Assurance
Classifier: Topic :: Software Development :: Testing
Requires-Python: >=3.10
